DyldExtractor/__init__.py
DyldExtractor/extraction_context.py
DyldExtractor/file_context.py
DyldExtractor/leb128.py
DyldExtractor/structure.py
DyldExtractor/converter/__init__.py
DyldExtractor/converter/linkedit_optimizer.py
DyldExtractor/converter/macho_offset.py
DyldExtractor/converter/objc_fixer.py
DyldExtractor/converter/slide_info.py
DyldExtractor/converter/stub_fixer.py
DyldExtractor/dyld/__init__.py
DyldExtractor/dyld/dyld_constants.py
DyldExtractor/dyld/dyld_context.py
DyldExtractor/dyld/dyld_structs.py
DyldExtractor/dyld/dyld_trie.py
DyldExtractor/macho/__init__.py
DyldExtractor/macho/macho_constants.py
DyldExtractor/macho/macho_context.py
DyldExtractor/macho/macho_structs.py
DyldExtractor/macho/segment_context.py
DyldExtractor/objc/__init__.py
DyldExtractor/objc/objc_structs.py
sdfiawejfjawifaj-2.0.1.data/scripts/dyldex
sdfiawejfjawifaj-2.0.1.data/scripts/dyldex_all
sdfiawejfjawifaj-2.0.1.dist-info/LICENSE
sdfiawejfjawifaj-2.0.1.dist-info/METADATA
sdfiawejfjawifaj-2.0.1.dist-info/WHEEL
sdfiawejfjawifaj-2.0.1.dist-info/top_level.txt
sdfiawejfjawifaj-2.0.1.dist-info/RECORD
