Metadata-Version: 2.1
Name: sdfiawejfjawifaj
Version: 2.0.1
Summary: Extract Binaries from Apple's Dyld Shared Cache
Home-page: https://github.com/arandomdev/dyldextractor
Author: arandomdev
License: UNKNOWN
Platform: UNKNOWN
Classifier: Programming Language :: Python :: 3
Classifier: License :: OSI Approved :: MIT License
Classifier: Operating System :: OS Independent
Requires-Python: >=3.8
License-File: LICENSE
Requires-Dist: progressbar2
Requires-Dist: capstone (==4.0.2)
